tkdialog/__init__.py
tkdialog/dialog.py
tkdialog_wrapper-2.1.0.dist-info/LICENSE
tkdialog_wrapper-2.1.0.dist-info/METADATA
tkdialog_wrapper-2.1.0.dist-info/WHEEL
tkdialog_wrapper-2.1.0.dist-info/top_level.txt
tkdialog_wrapper-2.1.0.dist-info/RECORD
