Metadata-Version: 2.1
Name: tkdialog-wrapper
Version: 2.1.0
Summary: A wrapper library to use tkinter dialogs easily.
Home-page: https://github.com/KosukeMizuno/tkdialog
License: MIT
Platform: UNKNOWN
Classifier: Programming Language :: Python :: 3
Classifier: Programming Language :: Python :: 3.5
Requires-Python: >=3.5
